smilepyerror/ErrorBase.py
SmilePyError-1.0.2.dist-info/LICENSE.txt
SmilePyError-1.0.2.dist-info/METADATA
SmilePyError-1.0.2.dist-info/WHEEL
SmilePyError-1.0.2.dist-info/top_level.txt
SmilePyError-1.0.2.dist-info/RECORD
